LICENSE
README.md
setup.py
scann/__init__.py
scann/layers/__init__.py
scann/layers/attention.py
scann/layers/custom_layers.py
scann/layers/losses.py
scann/models/__init__.py
scann/models/scann_model.py
scann/utils/__init__.py
scann/utils/datagenerator.py
scann/utils/general.py
scann/utils/voronoi_neighbor.py
scann/utils/dataset/__init__.py
scann/utils/dataset/atomic_data.py
scann/utils/dataset/fullerene.py
scann/utils/dataset/mp2018.py
scann/utils/dataset/pt_graphene.py
scann/utils/dataset/qm9.py
scann/utils/dataset/qm9_std_jctc.py
scann/utils/dataset/smfe.py
scann_model.egg-info/PKG-INFO
scann_model.egg-info/SOURCES.txt
scann_model.egg-info/dependency_links.txt
scann_model.egg-info/requires.txt
scann_model.egg-info/top_level.txt