Metadata-Version: 2.1
Name: scann-model
Version: 1.0
Summary: SCANN - Self-Consistent Atention-based Neural Network
Home-page: https://github.com/sinhvt3421/scann--material
Author: Vu Tien-Sinh
Author-email: sinh.vt@jaist.ac.jp
License: MIT
Keywords: materials,science,interpretable,deep,attention,networks,neural
Classifier: Development Status :: 4 - Beta
Classifier: Intended Audience :: Science/Research
Classifier: License :: OSI Approved :: MIT License
Classifier: Operating System :: OS Independent
Classifier: Programming Language :: Python :: 3.9
Classifier: Programming Language :: Python :: 3.10
Classifier: Topic :: Scientific/Engineering :: Physics
Classifier: Topic :: Software Development :: Libraries :: Python Modules
Requires-Python: >=3.9
Provides-Extra: test
License-File: LICENSE
